<annotation>
	<folder>Tomato_annotation</folder>
	<filename>53_0.jpg</filename>
	<path>/Users/choejongmun/Desktop/paper/高知県/Tomato_annotation/53_0.jpg</path>
	<source>
		<database>Unknown</database>
	</source>
	<size>
		<width>668</width>
		<height>712</height>
		<depth>3</depth>
	</size>
	<segmented>0</segmented>
	<object>
		<name>tomato</name>
		<pose>Unspecified</pose>
		<truncated>0</truncated>
		<difficult>0</difficult>
		<bndbox>
			<xmin>25</xmin>
			<ymin>46</ymin>
			<xmax>658</xmax>
			<ymax>684</ymax>
		</bndbox>
	</object>
</annotation>
